LICENSE
README.md
setup.py
src/te_eg_usage.py
src/te_eg_usage.egg-info/PKG-INFO
src/te_eg_usage.egg-info/SOURCES.txt
src/te_eg_usage.egg-info/dependency_links.txt
src/te_eg_usage.egg-info/entry_points.txt
src/te_eg_usage.egg-info/requires.txt
src/te_eg_usage.egg-info/top_level.txt