Metadata-Version: 2.1
Name: te-eg-usage
Version: 1.0.1
Summary: Telecome Egypt Usage - Selenium simple scraper to get your data usage info
Home-page: https://github.com/FaresAhmedb/te-eg-usage
Author: Fares Ahmed
Author-email: faresahmed@zohomail.com
License: GPLv3
Platform: UNKNOWN
Requires-Python: >=3.4
